README.md
setup.cfg
setup.py
function_log/__init__.py
function_log.egg-info/PKG-INFO
function_log.egg-info/SOURCES.txt
function_log.egg-info/dependency_links.txt
function_log.egg-info/not-zip-safe
function_log.egg-info/top_level.txt