Metadata-Version: 1.0
Name: function-log
Version: 0.4
Summary: Logging and timing tests for Python functions
Home-page: https://github.com/dibsonthis/function_log
Author: Adib Attie
Author-email: adib.attie33@gmail.com
License: MIT
Platform: UNKNOWN
